[
  {
    "type": "image",
    "merged_json": "data/merged\\南关煤业小煤柱沿空掘巷切顶卸压技术分析_樊彦武_merged.json",
    "page_num": 1,
    "image_index": 0,
    "thought": "该论文聚焦于煤矿开采中‘切顶卸压’技术以控制围岩应力、保障邻近工作面巷道稳定性。核心技术点包括：1）关键层理论指导下的切顶参数设计（高度6m/12m、角度70°/120°）；2）数值模拟方法（FLAC3D）用于应力场分析；3）基于应力分布云图的卸压效果评估；4）小煤柱合理尺寸反演（与应力降低区范围直接关联）。技术体系呈‘理论指导→参数设计→数值仿真→效果验证→工程决策’的递进结构，核心目标是通过切顶干预改变应力重分布，扩大低应力区，从而支持安全合理的煤柱留设。",
    "tree": {
      "root": "煤矿切顶卸压技术体系",
      "children": [
        {
          "name": "理论基础",
          "children": [
            {
              "name": "关键层理论"
            },
            {
              "name": "原岩应力与应力集中机制"
            }
          ]
        },
        {
          "name": "参数设计",
          "children": [
            {
              "name": "切顶高度（6 m / 12 m）"
            },
            {
              "name": "切顶角度（70° / 120°）"
            },
            {
              "name": "钻孔方位（偏向邻近工作面侧）"
            }
          ]
        },
        {
          "name": "数值仿真",
          "children": [
            {
              "name": "FLAC3D建模"
            },
            {
              "name": "网格划分（1 m/格稀疏网格）"
            },
            {
              "name": "工况设置（5种切顶方案）"
            },
            {
              "name": "应力场输出（垂直应力云图）"
            }
          ]
        },
        {
          "name": "效果评估",
          "children": [
            {
              "name": "应力峰值变化（17.96 → 14.44 MPa）"
            },
            {
              "name": "应力降低区范围扩展（4 m → 12 m）"
            },
            {
              "name": "应力集中系数计算（2.39等）"
            }
          ]
        },
        {
          "name": "工程决策",
          "children": [
            {
              "name": "小煤柱宽度优化（1.8 m → 7.8 m）"
            },
            {
              "name": "安全性校核（漏风、自燃风险）"
            },
            {
              "name": "最优方案确定（120° + 12 m）"
            }
          ]
        }
      ]
    },
    "auto_annotated": true,
    "needs_review": true
  },
  {
    "type": "image",
    "merged_json": "data/merged\\南关煤业小煤柱沿空掘巷切顶卸压技术分析_樊彦武_merged.json",
    "page_num": 1,
    "image_index": 1,
    "thought": "论文聚焦于煤矿开采中‘切顶卸压’技术，核心是通过调整切顶钻孔的几何参数（高度、角度）来调控采空区侧向围岩应力分布，从而优化小煤柱尺寸以保障巷道稳定性和防止自燃。关键技术点包括：1）关键层理论指导下的切顶设计；2）数值模拟（FLAC3D）作为分析工具；3）五种工况对比（含未切顶基准与四种切顶方案）；4）应力降低区范围与峰值应力作为评价指标；5）最终目标是确定最优切顶参数（12 m高度 + 120°角度）以支持合理煤柱宽度（7.8 m）设计。技术体系呈现‘理论指导→参数设计→数值验证→工程决策’的层级结构。",
    "tree": {
      "root": "煤矿切顶卸压技术体系",
      "children": [
        {
          "name": "理论基础",
          "children": [
            {
              "name": "关键层理论",
              "children": []
            }
          ]
        },
        {
          "name": "参数设计",
          "children": [
            {
              "name": "切顶高度",
              "children": [
                {
                  "name": "6 m",
                  "children": []
                },
                {
                  "name": "12 m",
                  "children": []
                }
              ]
            },
            {
              "name": "切顶角度",
              "children": [
                {
                  "name": "70°（偏向工作面侧）",
                  "children": []
                },
                {
                  "name": "120°（反向）",
                  "children": []
                }
              ]
            },
            {
              "name": "方位与钻孔布置",
              "children": []
            }
          ]
        },
        {
          "name": "数值模拟验证",
          "children": [
            {
              "name": "FLAC3D建模",
              "children": []
            },
            {
              "name": "工况对比分析",
              "children": [
                {
                  "name": "工况0：未切顶",
                  "children": []
                },
                {
                  "name": "工况1：6 m + 70°",
                  "children": []
                },
                {
                  "name": "工况2：12 m + 70°",
                  "children": []
                },
                {
                  "name": "工况3：6 m + 120°",
                  "children": []
                },
                {
                  "name": "工况4：12 m + 120°",
                  "children": []
                }
              ]
            },
            {
              "name": "应力评估指标",
              "children": [
                {
                  "name": "垂直应力峰值",
                  "children": []
                },
                {
                  "name": "应力降低区范围",
                  "children": []
                },
                {
                  "name": "应力集中系数",
                  "children": []
                }
              ]
            }
          ]
        },
        {
          "name": "工程决策输出",
          "children": [
            {
              "name": "小煤柱合理宽度",
              "children": [
                {
                  "name": "≤1.8 m（方案1）",
                  "children": []
                },
                {
                  "name": "≤3.8 m（方案2/3）",
                  "children": []
                },
                {
                  "name": "≤7.8 m（方案4，最优）",
                  "children": []
                }
              ]
            },
            {
              "name": "稳定性与安全约束",
              "children": [
                {
                  "name": "巷道稳定性保障",
                  "children": []
                },
                {
                  "name": "防漏风与防自燃要求",
                  "children": []
                }
              ]
            },
            {
              "name": "最优方案",
              "children": [
                {
                  "name": "12 m切顶高度 + 120°切顶角度",
                  "children": []
                }
              ]
            }
          ]
        }
      ]
    },
    "auto_annotated": true,
    "needs_review": true
  },
  {
    "type": "image",
    "merged_json": "data/merged\\南关煤业小煤柱沿空掘巷切顶卸压技术分析_樊彦武_merged.json",
    "page_num": 1,
    "image_index": 2,
    "thought": "论文聚焦于煤矿开采中‘切顶卸压’技术对围岩应力调控的作用，核心是通过调整切顶钻孔的几何参数（高度、角度）来扩大采空区侧向应力降低区，从而为小煤柱与巷道布置提供安全空间。关键技术点包括：1）关键层理论指导下的切顶设计；2）数值模拟（FLAC3D）作为分析工具；3）切顶参数（高度6m/12m、角度70°/120°）的多工况对比；4）应力分布特征（峰值、降低区范围、集中系数）作为评价指标；5）最终目标是确定合理小煤柱尺寸以保障巷道稳定并防止漏风自燃。整个技术体系以‘应力调控’为核心目标，由理论指导、参数设计、仿真验证、工程决策四层构成。",
    "tree": {
      "root": "煤矿切顶卸压应力调控技术体系",
      "children": [
        {
          "name": "理论基础",
          "children": [
            {
              "name": "关键层理论"
            },
            {
              "name": "原岩应力场分析（如7.5 MPa基准）"
            }
          ]
        },
        {
          "name": "参数化设计",
          "children": [
            {
              "name": "切顶高度（6 m / 12 m）"
            },
            {
              "name": "切顶角度（与顶板夹角：70° / 120°）"
            },
            {
              "name": "钻孔方位（偏向1207工作面侧）"
            }
          ]
        },
        {
          "name": "数值仿真验证",
          "children": [
            {
              "name": "FLAC3D建模与计算"
            },
            {
              "name": "垂直应力云图分析（图1 a-e）"
            },
            {
              "name": "关键指标提取：应力峰值、降低区范围、集中系数"
            }
          ]
        },
        {
          "name": "工程决策输出",
          "children": [
            {
              "name": "最优方案确定（120° + 12 m）"
            },
            {
              "name": "小煤柱合理宽度设计（≤7.8 m）"
            },
            {
              "name": "巷道稳定性与防自燃协同控制"
            }
          ]
        }
      ]
    },
    "auto_annotated": true,
    "needs_review": true
  },
  {
    "type": "image",
    "merged_json": "data/merged\\南关煤业小煤柱沿空掘巷切顶卸压技术分析_樊彦武_merged.json",
    "page_num": 1,
    "image_index": 3,
    "thought": "该论文聚焦于煤矿开采中‘切顶卸压’技术在小煤柱巷道稳定性控制中的应用。核心是通过调整切顶钻孔的几何参数（高度、角度）来改变采空区侧向围岩应力分布，从而扩大应力降低区范围，为合理设计小煤柱宽度提供依据。关键技术点包括：1）关键层理论指导下的切顶参数设计（高度6m/12m、角度70°/120°）；2）数值模拟（FLAC3D）作为分析工具，量化应力分布与集中系数；3）以应力峰值、降低区范围、小煤柱宽度为评价指标，形成‘参数设计→模拟验证→工程优化’的技术闭环。整体属于矿山岩体力学与绿色开采交叉领域，技术体系以‘卸压机理’为核心，向上支撑巷道布置决策，向下依赖数值建模与现场实测验证。",
    "tree": {
      "root": "煤矿切顶卸压协同小煤柱稳定性控制技术体系",
      "children": [
        {
          "name": "理论基础",
          "children": [
            "关键层理论",
            "原岩应力场分析",
            "应力集中与卸压机理"
          ]
        },
        {
          "name": "核心技术方法",
          "children": [
            {
              "name": "切顶参数设计",
              "children": [
                "切顶高度（6 m / 12 m）",
                "切顶角度（与顶板夹角：70° / 120°）",
                "钻孔方位（偏向邻近工作面侧）"
              ]
            },
            {
              "name": "数值模拟分析",
              "children": [
                "FLAC3D建模",
                "垂直应力云图分析",
                "应力峰值与集中系数计算",
                "应力降低区范围量化"
              ]
            }
          ]
        },
        {
          "name": "工程应用输出",
          "children": [
            "小煤柱合理宽度确定（如7.8 m）",
            "巷道布置优化",
            "防漏风与防自燃协同设计",
            "最优方案决策（120° + 12 m）"
          ]
        },
        {
          "name": "验证与反馈",
          "children": [
            "1205/1207工作面实测应力数据",
            "多工况对比分析（5种方案）",
            "工程可行性评估"
          ]
        }
      ]
    },
    "auto_annotated": true,
    "needs_review": true
  },
  {
    "type": "image",
    "merged_json": "data/merged\\南关煤业小煤柱沿空掘巷切顶卸压技术分析_樊彦武_merged.json",
    "page_num": 1,
    "image_index": 4,
    "thought": "论文聚焦于煤矿开采中‘切顶卸压’技术对围岩应力调控的作用，核心是通过调整切顶钻孔的几何参数（高度、角度）来扩大采空区侧向应力降低区，从而为小煤柱与巷道布置提供安全空间。关键技术点包括：1）关键层理论作为理论基础；2）数值模拟（FLAC3D）作为分析工具；3）切顶参数（高度6m/12m、角度70°/120°）作为调控手段；4）应力分布特征（峰值、降低区范围、集中系数）作为评价指标；5）小煤柱合理尺寸（如7.8m）作为工程目标。整体技术体系以‘理论指导—参数设计—数值验证—工程优化’为主线，形成闭环决策流程。",
    "tree": {
      "root": "煤矿切顶卸压技术体系",
      "children": [
        {
          "name": "理论基础",
          "children": [
            {
              "name": "关键层理论"
            }
          ]
        },
        {
          "name": "核心方法",
          "children": [
            {
              "name": "切顶钻孔参数设计",
              "children": [
                {
                  "name": "切顶高度（6m / 12m）"
                },
                {
                  "name": "切顶角度（与顶板夹角：70° / 120°）"
                },
                {
                  "name": "方位控制（偏向邻近工作面侧）"
                }
              ]
            },
            {
              "name": "数值模拟分析",
              "children": [
                {
                  "name": "FLAC3D建模与计算"
                },
                {
                  "name": "应力云图可视化（垂直应力分布）"
                }
              ]
            }
          ]
        },
        {
          "name": "评价指标",
          "children": [
            {
              "name": "应力峰值（MPa）"
            },
            {
              "name": "应力降低区范围（m）"
            },
            {
              "name": "应力集中系数"
            },
            {
              "name": "小煤柱合理宽度（m）"
            }
          ]
        },
        {
          "name": "工程目标",
          "children": [
            {
              "name": "保障巷道稳定性"
            },
            {
              "name": "抑制漏风与自燃风险"
            },
            {
              "name": "确定最优切顶方案（120° + 12m）"
            }
          ]
        }
      ]
    },
    "auto_annotated": true,
    "needs_review": true
  }
]