[
  {
    "type": "image",
    "merged_json": "data/merged\\基于AI的动力电池性能监测专利技术分析_唐进岭 (1)_merged.json",
    "page_num": 1,
    "image_index": 0,
    "thought": "论文聚焦于动力电池性能监测技术体系，核心围绕‘状态感知—数据处理—智能决策’三层逻辑展开：1）底层是多源传感器（电压、电流、温度、内阻等）实现对SOC、SOH、RUL、SOE、EOL等关键参数的实时采集；2）中层依托LabVIEW等工具与大数据平台进行数据预处理与特征提取；3）上层融合AI（特别是神经网络与深度学习）实现健康评估、容量预测与故障预警。技术演进路径体现为从人工/仪表→自动化→智能化，AI已成为贯穿电池全生命周期管理的核心驱动力。专利趋势图显示2018年后申请量显著上升，印证AI驱动的智能监测成为主流方向。",
    "tree": {
      "root": "动力电池智能性能监测技术体系",
      "children": [
        {
          "name": "1. 状态感知层",
          "children": [
            {
              "name": "1.1 传感硬件",
              "children": [
                "电压传感器",
                "电流传感器",
                "温度传感器",
                "内阻检测模块"
              ]
            },
            {
              "name": "1.2 关键状态参数",
              "children": [
                "荷电状态（SOC）",
                "健康状态（SOH）",
                "剩余寿命（RUL）",
                "能量状态（SOE）",
                "寿命终止点（EOL）"
              ]
            }
          ]
        },
        {
          "name": "2. 数据处理层",
          "children": [
            {
              "name": "2.1 数据采集与传输",
              "children": [
                "BMS数据总线",
                "无线通信模块（CAN/LIN/5G）"
              ]
            },
            {
              "name": "2.2 数据分析平台",
              "children": [
                "LabVIEW实时分析系统",
                "边缘计算节点",
                "云计算平台"
              ]
            }
          ]
        },
        {
          "name": "3. 智能决策层",
          "children": [
            {
              "name": "3.1 AI算法模型",
              "children": [
                "神经网络（ANN）",
                "深度学习（LSTM/GRU）",
                "强化学习",
                "迁移学习"
              ]
            },
            {
              "name": "3.2 应用功能",
              "children": [
                "实时状态估计",
                "容量衰减预测",
                "故障早期预警",
                "寿命优化管理",
                "安全风险评估"
              ]
            }
          ]
        },
        {
          "name": "4. 技术支撑与演进",
          "children": [
            {
              "name": "4.1 基础方法",
              "children": [
                "静态特性测试",
                "动态特性测试",
                "温度特性测试"
              ]
            },
            {
              "name": "4.2 发展趋势",
              "children": [
                "人工→自动化→智能化",
                "单点监测→多维融合评估",
                "离线分析→在线闭环控制"
              ]
            }
          ]
        }
      ]
    },
    "auto_annotated": true,
    "needs_review": true
  },
  {
    "type": "image",
    "merged_json": "data/merged\\基于AI的动力电池性能监测专利技术分析_唐进岭 (1)_merged.json",
    "page_num": 2,
    "image_index": 0,
    "thought": "论文聚焦于动力电池性能监测领域，核心是通过AI技术对关键状态参数（SOC、SOE、RUL、EOL）进行实时监测与预测，以实现电池健康管理与寿命延长。其中，SOC（荷电状态）和SOE（能量状态）属于**状态感知层**，反映电池当前物理状态；RUL（剩余使用寿命）和EOL（寿命终止点）属于**健康评估与预测层**，依赖历史数据与AI模型进行趋势推断；而AI技术（如机器学习、深度学习）构成**智能分析层**，支撑从感知到预测的闭环。专利检索以这四类参数为关键词，表明其为该技术体系的核心指标。整体架构呈现‘感知→建模→预测→决策’的技术链条，根节点应为‘动力电池智能健康监测技术体系’。",
    "tree": {
      "root": "动力电池智能健康监测技术体系",
      "children": [
        {
          "name": "状态感知层",
          "children": [
            {
              "name": "SOC（荷电状态）估算"
            },
            {
              "name": "SOE（能量状态）估算"
            }
          ]
        },
        {
          "name": "健康评估与预测层",
          "children": [
            {
              "name": "RUL（剩余使用寿命）预测"
            },
            {
              "name": "EOL（寿命终止点）判定"
            }
          ]
        },
        {
          "name": "智能分析层",
          "children": [
            {
              "name": "AI驱动建模（机器学习/深度学习）"
            },
            {
              "name": "多源数据融合与特征工程"
            }
          ]
        },
        {
          "name": "应用决策层",
          "children": [
            {
              "name": "充放电策略优化"
            },
            {
              "name": "预防性维护与更换决策"
            },
            {
              "name": "系统可靠性保障"
            }
          ]
        }
      ]
    },
    "auto_annotated": true,
    "needs_review": true
  },
  {
    "type": "image",
    "merged_json": "data/merged\\基于AI的动力电池性能监测专利技术分析_唐进岭 (1)_merged.json",
    "page_num": 3,
    "image_index": 0,
    "thought": "论文聚焦于电池性能监测领域的技术发展与专利布局，明确指出其快速发展与深度学习技术（特别是CNN、RNN、LSTM等神经网络模型）的成熟直接相关。核心应用场景是‘电池性能监测’，技术驱动力为AI/机器学习算法；专利数据表明中国在该领域占据绝对主导地位，反映技术落地与产业化高度集中于中国。因此，该技术体系应以‘电池智能监测’为根节点，上层依赖AI算法支撑，下层关联硬件感知与系统集成，形成‘感知-算法-决策-应用’闭环结构。",
    "tree": {
      "root": "电池智能性能监测技术体系",
      "children": [
        {
          "name": "感知层：多模态数据采集",
          "children": [
            {
              "name": "电压/电流传感器"
            },
            {
              "name": "温度传感器"
            },
            {
              "name": "内阻/阻抗谱采集模块"
            },
            {
              "name": "声学/光学特征采集（如超声、红外）"
            }
          ]
        },
        {
          "name": "算法层：AI驱动的分析模型",
          "children": [
            {
              "name": "卷积神经网络（CNN）——用于时频域特征提取（如电压曲线图像化分析）"
            },
            {
              "name": "循环神经网络（RNN）与LSTM——用于时序建模（如充放电过程动态预测）"
            },
            {
              "name": "图神经网络（GNN）——用于电池组拓扑关系建模（隐含于系统级监测）"
            },
            {
              "name": "迁移学习/小样本学习——应对标注数据稀缺问题"
            }
          ]
        },
        {
          "name": "决策层：状态评估与预警",
          "children": [
            {
              "name": "健康状态（SOH）估计"
            },
            {
              "name": "荷电状态（SOC）校准"
            },
            {
              "name": "剩余使用寿命（RUL）预测"
            },
            {
              "name": "故障诊断与早期预警（如热失控前兆识别）"
            }
          ]
        },
        {
          "name": "应用层：系统集成与产业落地",
          "children": [
            {
              "name": "电动汽车BMS智能升级"
            },
            {
              "name": "储能电站寿命管理平台"
            },
            {
              "name": "梯次利用评估系统"
            },
            {
              "name": "知识产权保护与标准构建（呼应文中专利激增现象）"
            }
          ]
        }
      ]
    },
    "auto_annotated": true,
    "needs_review": true
  },
  {
    "type": "image",
    "merged_json": "data/merged\\基于AI的动力电池性能监测专利技术分析_唐进岭 (1)_merged.json",
    "page_num": 3,
    "image_index": 1,
    "thought": "论文聚焦于电池性能监测领域的技术发展，明确指出其快速发展与深度学习技术（特别是CNN、RNN、LSTM等神经网络模型）的成熟直接相关。文中强调AI算法为电池监测提供‘强有力的算法支持’，并实现‘精准获取监测数据’，说明该领域技术体系以AI驱动的智能监测为核心。结合专利申请趋势（中国主导、2019年起爆发），可推断技术体系结构应以‘智能电池性能监测’为根节点，下层分为数据感知层（传感器/数据采集）、算法模型层（深度学习核心模型）、应用服务层（状态评估、预测、决策支持）。图2虽为专利来源国分布，但未提供具体技术架构图；因此需依据文本逻辑反推：核心技术驱动力是深度学习模型，应用场景是电池性能监测，故树状结构应体现‘感知→建模→应用’的技术链条。",
    "tree": {
      "root": "智能电池性能监测技术体系",
      "children": [
        {
          "name": "数据感知与采集层",
          "children": [
            {
              "name": "多模态传感器网络（电压、电流、温度、内阻等）"
            },
            {
              "name": "边缘计算设备与实时数据预处理"
            }
          ]
        },
        {
          "name": "智能算法模型层",
          "children": [
            {
              "name": "卷积神经网络（CNN）——用于特征提取与图像/时序信号分析"
            },
            {
              "name": "循环神经网络（RNN）与长短期记忆网络（LSTM）——用于时序建模与状态演化预测"
            },
            {
              "name": "混合模型与迁移学习——提升小样本泛化能力"
            }
          ]
        },
        {
          "name": "应用与决策支持层",
          "children": [
            {
              "name": "健康状态（SOH）评估"
            },
            {
              "name": "剩余寿命（RUL）预测"
            },
            {
              "name": "故障诊断与早期预警"
            },
            {
              "name": "能效优化与充电策略生成"
            }
          ]
        }
      ]
    },
    "auto_annotated": true,
    "needs_review": true
  },
  {
    "type": "image",
    "merged_json": "data/merged\\基于AI的动力电池性能监测专利技术分析_唐进岭 (1)_merged.json",
    "page_num": 4,
    "image_index": 0,
    "thought": "论文聚焦于基于AI的动力电池性能监测技术的专利分析，核心在于：1）主分类号G01R（测量电/磁变量）是该领域的核心技术主线，尤其子类G01R31/392和G01R31/367直接对应电池健康状态（SOH）与剩余寿命（RUL）预测、功率能力估计等关键任务；2）AI算法（如麻雀搜索优化LSSVR、非线性模型预测控制）作为方法层支撑，属于G06F（电数字数据处理）范畴；3）G06Q（商业/管理ICT）作为副分类号，反映技术向系统集成与应用落地延伸；4）中国在该领域专利申请量占绝对优势（>50%），体现产业驱动特征。技术体系可归纳为：以‘电池性能测量’为根，向下分出‘物理量感知与建模’（G01R）、‘智能算法处理’（G06F）、‘应用系统集成’（G06Q）三层结构。",
    "tree": {
      "root": "基于AI的动力电池性能监测技术",
      "children": [
        {
          "name": "物理量感知与建模（主分类：G01R）",
          "children": [
            {
              "name": "电池健康状态（SOH）估计",
              "children": [
                {
                  "name": "基于优化算法的LSSVR建模（如麻雀搜索优化）",
                  "children": []
                }
              ]
            },
            {
              "name": "剩余寿命（RUL）预测",
              "children": []
            },
            {
              "name": "功率能力估计",
              "children": [
                {
                  "name": "非线性模型预测控制（NMPC）优化求解",
                  "children": []
                }
              ]
            }
          ]
        },
        {
          "name": "智能算法处理（分类：G06F）",
          "children": [
            {
              "name": "机器学习模型",
              "children": [
                {
                  "name": "最小二乘支持向量机（LSSVR）",
                  "children": []
                },
                {
                  "name": "其他回归/分类模型",
                  "children": []
                }
              ]
            },
            {
              "name": "元启发式优化算法",
              "children": [
                {
                  "name": "麻雀搜索算法（SSA）",
                  "children": []
                },
                {
                  "name": "遗传算法、粒子群等",
                  "children": []
                }
              ]
            },
            {
              "name": "数值优化与求解器",
              "children": []
            }
          ]
        },
        {
          "name": "应用系统集成与管理（副分类：G06Q）",
          "children": [
            {
              "name": "电池管理系统（BMS）智能化升级",
              "children": []
            },
            {
              "name": "云端监测与运维平台",
              "children": []
            },
            {
              "name": "商业/金融场景适配（如电池残值评估、保险定价）",
              "children": []
            }
          ]
        }
      ]
    },
    "auto_annotated": true,
    "needs_review": true
  }
]