[
  {
    "type": "image",
    "merged_json": "data/merged\\家禽孵化器产业发展方向分析_刘振_merged.json",
    "page_num": 0,
    "image_index": 0,
    "thought": "论文聚焦家禽孵化器的核心工作原理与技术演进，明确指出其关键技术环节包括：温度控制（核心，精度要求高）、湿度控制（±3%精度）、通风换气、翻蛋、照蛋检查、移蛋与出雏。这些功能共同构成孵化环境模拟系统。专利分析显示技术发展呈上升趋势，尤其2012年后加速，反映自动化、精准化、智能化是主流方向。虽未直接提及具体技术层级，但可推断：底层为传感与执行硬件（温湿度传感器、加湿泵、风扇、翻蛋机构等），中层为控制逻辑与算法（PID温控、反馈调节），上层为集成管理系统（含照蛋、移蛋等流程协同）。因此技术体系应以‘智能孵化环境调控系统’为根节点，下分环境参数控制、机械操作执行、监测与决策支持三大支柱。",
    "tree": {
      "root": "智能家禽孵化器技术体系",
      "children": [
        {
          "name": "环境参数精准调控子系统",
          "children": [
            {
              "name": "温度控制模块",
              "children": [
                {
                  "name": "高精度温控传感器"
                },
                {
                  "name": "PID/模糊控制算法"
                },
                {
                  "name": "加热元件（如电热丝、PTC）"
                }
              ]
            },
            {
              "name": "湿度控制模块",
              "children": [
                {
                  "name": "湿度传感器"
                },
                {
                  "name": "自动调湿装置（水盘/加湿泵）"
                },
                {
                  "name": "闭环反馈调节机制"
                }
              ]
            },
            {
              "name": "通风换气模块",
              "children": [
                {
                  "name": "CO₂/O₂浓度监测"
                },
                {
                  "name": "变频风机控制"
                },
                {
                  "name": "气流均匀分布设计"
                }
              ]
            }
          ]
        },
        {
          "name": "机械操作执行子系统",
          "children": [
            {
              "name": "自动翻蛋机构",
              "children": [
                {
                  "name": "定时/角度可控翻转装置"
                },
                {
                  "name": "蛋盘驱动电机与传动结构"
                }
              ]
            },
            {
              "name": "移蛋与出雏自动化",
              "children": [
                {
                  "name": "蛋位识别与定位"
                },
                {
                  "name": "机械臂/传送带协同系统"
                }
              ]
            }
          ]
        },
        {
          "name": "监测与智能决策子系统",
          "children": [
            {
              "name": "照蛋检查模块",
              "children": [
                {
                  "name": "光学成像与图像识别"
                },
                {
                  "name": "胚胎发育状态评估算法"
                }
              ]
            },
            {
              "name": "数据采集与中央控制",
              "children": [
                {
                  "name": "多源传感器融合"
                },
                {
                  "name": "嵌入式控制器（MCU/PLC）"
                },
                {
                  "name": "人机交互界面与远程监控"
                }
              ]
            },
            {
              "name": "孵化过程优化模型",
              "children": [
                {
                  "name": "基于历史数据的预测模型"
                },
                {
                  "name": "自适应参数调整策略"
                }
              ]
            }
          ]
        }
      ]
    },
    "auto_annotated": true,
    "needs_review": true
  },
  {
    "type": "image",
    "merged_json": "data/merged\\家禽孵化器产业发展方向分析_刘振_merged.json",
    "page_num": 1,
    "image_index": 0,
    "thought": "该论文聚焦于家禽孵化器领域的专利技术分布与申请人格局，核心并非描述具体技术实现细节，而是通过专利数据揭示产业技术体系的地理与主体结构。文中反复强调‘自动化系统’‘环境自动化控制系统’‘实时监控’‘自动调节’等关键词，结合荷特集团（Hotraco）的专长，可推断该领域技术体系以‘智能环境控制’为核心，涵盖感知层（温湿度/气体/光照等传感器）、控制层（PLC/嵌入式控制器）、执行层（加热/通风/翻蛋/加湿等执行机构）及系统集成（数据反馈闭环调节）。中国虽申请量最多，但企业多为国内布局、技术偏重设备制造；而荷兰Hotraco等国际领先企业则强调全流程自动化与跨国专利布局，体现‘硬件+软件+服务’融合的高阶技术体系。因此，技术体系结构应以‘智能孵化控制系统’为根节点，下分感知、控制、执行、系统集成四大支柱。",
    "tree": {
      "root": "智能家禽孵化器技术体系",
      "children": [
        {
          "name": "环境感知层",
          "children": [
            {
              "name": "温湿度传感"
            },
            {
              "name": "CO₂/O₂浓度监测"
            },
            {
              "name": "光照强度检测"
            },
            {
              "name": "蛋壳温度非接触测量"
            }
          ]
        },
        {
          "name": "智能控制层",
          "children": [
            {
              "name": "PLC/嵌入式控制器"
            },
            {
              "name": "模糊PID算法"
            },
            {
              "name": "自适应阈值调节"
            },
            {
              "name": "多参数耦合决策模型"
            }
          ]
        },
        {
          "name": "执行机构层",
          "children": [
            {
              "name": "恒温加热系统"
            },
            {
              "name": "变频通风装置"
            },
            {
              "name": "机械/气动翻蛋机构"
            },
            {
              "name": "雾化加湿模块"
            }
          ]
        },
        {
          "name": "系统集成与服务层",
          "children": [
            {
              "name": "远程监控平台（IoT）"
            },
            {
              "name": "数据驱动优化算法"
            },
            {
              "name": "全生命周期管理软件"
            },
            {
              "name": "跨国专利布局策略"
            }
          ]
        }
      ]
    },
    "auto_annotated": true,
    "needs_review": true
  },
  {
    "type": "image",
    "merged_json": "data/merged\\家禽孵化器产业发展方向分析_刘振_merged.json",
    "page_num": 2,
    "image_index": 0,
    "thought": "论文聚焦于家禽孵化器产业的专利布局与技术发展现状，核心内容包括：1）地域分布（安徽蚌埠领先，山东、江苏、广东等紧随其后）；2）主要申请人（如安徽瑞格电子、青岛兴仪电子，体现企业主导的研发模式）；3）关键技术改进点明确指向‘加热装置’和‘翻蛋装置’两大核心子系统；4）指出当前专利质量不高（发明专利占比低、有效发明少）、缺乏海外布局风险。结合行业特性，家禽孵化器属于智能养殖装备，其技术体系应以‘温控-机械执行-系统集成’为主线，其中加热与翻蛋是核心功能模块，支撑整机智能化与自动化运行。因此，技术体系结构可归纳为：以‘智能家禽孵化器系统’为根节点，下分‘环境调控子系统’（含加热、通风、湿度控制）、‘机械执行子系统’（含翻蛋、出雏、托盘机构）、‘智能控制与感知子系统’（含传感器、PLC/嵌入式控制、人机交互），最终集成于‘整机系统与工程交付’层级。",
    "tree": {
      "root": "智能家禽孵化器技术体系",
      "children": [
        {
          "name": "环境调控子系统",
          "children": [
            {
              "name": "加热装置"
            },
            {
              "name": "通风与换气装置"
            },
            {
              "name": "湿度调控装置"
            }
          ]
        },
        {
          "name": "机械执行子系统",
          "children": [
            {
              "name": "翻蛋装置"
            },
            {
              "name": "托盘/蛋架驱动机构"
            },
            {
              "name": "出雏与清粪机构"
            }
          ]
        },
        {
          "name": "智能控制与感知子系统",
          "children": [
            {
              "name": "温度/湿度/CO₂传感器网络"
            },
            {
              "name": "PLC/嵌入式控制器"
            },
            {
              "name": "人机交互与远程监控系统"
            }
          ]
        },
        {
          "name": "整机系统与工程交付",
          "children": [
            {
              "name": "模块化整机集成设计"
            },
            {
              "name": "交钥匙工程解决方案"
            },
            {
              "name": "专利布局与知识产权管理"
            }
          ]
        }
      ]
    },
    "auto_annotated": true,
    "needs_review": true
  },
  {
    "type": "image",
    "merged_json": "data/merged\\家禽孵化器产业发展方向分析_刘振_merged.json",
    "page_num": 3,
    "image_index": 0,
    "thought": "论文聚焦于家禽孵化器关键技术改进，核心围绕两大功能模块：加热均匀性与翻蛋稳定性。从专利CN221011487U可见，加热装置通过‘转辊+驱动机构（电机/皮带/钢带/轮系）+加热板’构成动态热传导系统，实现鸡蛋滚动受热；从CN221011488U图示及描述可知，翻蛋装置采用多层托盘结构，结合机械联动（如齿轮、连杆、支撑架）实现同步稳定翻转，避免滑落。二者均属于孵化设备的‘核心执行子系统’，依赖于‘机械传动’与‘温控执行’两大底层支撑。整体技术体系以‘智能孵化设备’为根节点，下分‘热管理子系统’与‘运动控制子系统’，再细化至具体机构与部件。申请主体分布（皖、鲁、粤、沪）反映产业聚集特征，但技术架构上仍以机电一体化为核心。",
    "tree": {
      "root": "智能家禽孵化器技术体系",
      "children": [
        {
          "name": "热管理子系统",
          "children": [
            {
              "name": "均匀加热机构",
              "children": [
                {
                  "name": "加热板"
                },
                {
                  "name": "滚动式转辊阵列"
                },
                {
                  "name": "驱动传动链",
                  "children": [
                    {
                      "name": "电机"
                    },
                    {
                      "name": "皮带/钢带传动"
                    },
                    {
                      "name": "主动轮-从动轮-导向轮组"
                    }
                  ]
                },
                {
                  "name": "辅助散热/气流组件",
                  "children": [
                    {
                      "name": "扇叶"
                    },
                    {
                      "name": "风道设计"
                    }
                  ]
                }
              ]
            },
            {
              "name": "温度感知与反馈",
              "children": [
                {
                  "name": "温度传感器"
                },
                {
                  "name": "PID温控模块"
                }
              ]
            }
          ]
        },
        {
          "name": "运动控制子系统",
          "children": [
            {
              "name": "翻蛋执行机构",
              "children": [
                {
                  "name": "多层蛋托盘"
                },
                {
                  "name": "同步翻转联动装置",
                  "children": [
                    {
                      "name": "齿轮-连杆机构（如图中9,10）"
                    },
                    {
                      "name": "支撑架与限位结构（如A,B,C处）"
                    }
                  ]
                },
                {
                  "name": "防滑落约束设计",
                  "children": [
                    {
                      "name": "蛋槽凹槽定位"
                    },
                    {
                      "name": "侧向挡板/弹性压紧件"
                    }
                  ]
                }
              ]
            },
            {
              "name": "运动精度与稳定性保障",
              "children": [
                {
                  "name": "角度限位开关"
                },
                {
                  "name": "缓启动/缓停机构"
                }
              ]
            }
          ]
        },
        {
          "name": "整机集成与支撑平台",
          "children": [
            {
              "name": "箱体结构（保温/隔振）"
            },
            {
              "name": "电源与控制系统"
            },
            {
              "name": "人机交互界面"
            },
            {
              "name": "模块化装配框架"
            }
          ]
        }
      ]
    },
    "auto_annotated": true,
    "needs_review": true
  },
  {
    "type": "image",
    "merged_json": "data/merged\\家禽孵化器产业发展方向分析_刘振_merged.json",
    "page_num": 3,
    "image_index": 1,
    "thought": "论文聚焦于家禽孵化器关键技术改进，核心围绕‘均匀受热’与‘稳定翻蛋’两大痛点。从专利CN221011487U可见，加热装置通过机械传动系统（电机→皮带/钢带→主动轮/从动轮→转辊/滚轮）驱动鸡蛋旋转，实现动态均匀加热；而CN221011488U的翻蛋装置则强调结构稳定性（如齿轮、滚轴、限位结构），防止鸡蛋滑落。结合申请人分布（安徽、山东、广东等地企业为主），反映该领域以中小型设备制造商为主导，技术演进路径为：基础孵化箱体 → 热管理子系统（加热+温控） → 运动控制子系统（翻蛋+转动） → 整机集成与可靠性提升。因此技术体系应以‘智能孵化装备’为根节点，下分热力调控、机械运动、结构集成三大支柱。",
    "tree": {
      "root": "智能家禽孵化器技术体系",
      "children": [
        {
          "name": "热力调控子系统",
          "children": [
            {
              "name": "均匀加热机构",
              "children": [
                {
                  "name": "旋转式加热板"
                },
                {
                  "name": "转辊-电机驱动链（含皮带/钢带/轮系）"
                },
                {
                  "name": "辅助对流结构（扇叶、风道）"
                }
              ]
            },
            {
              "name": "温度感知与反馈",
              "children": [
                {
                  "name": "分布式温度传感器"
                },
                {
                  "name": "PID温控算法模块"
                }
              ]
            }
          ]
        },
        {
          "name": "机械运动子系统",
          "children": [
            {
              "name": "翻蛋执行机构",
              "children": [
                {
                  "name": "齿轮-滚轴协同翻转机构"
                },
                {
                  "name": "限位防脱结构（如L形板、固定架）"
                },
                {
                  "name": "间歇/连续翻蛋模式切换机制"
                }
              ]
            },
            {
              "name": "鸡蛋定位与输送",
              "children": [
                {
                  "name": "托盘/卡槽式蛋位固定"
                },
                {
                  "name": "传送带/钢带联动输送系统"
                }
              ]
            }
          ]
        },
        {
          "name": "整机集成与可靠性增强",
          "children": [
            {
              "name": "模块化箱体结构",
              "children": [
                {
                  "name": "多层叠放式布局"
                },
                {
                  "name": "隔热与密封设计"
                }
              ]
            },
            {
              "name": "故障防护与容错",
              "children": [
                {
                  "name": "鸡蛋跌落检测与急停"
                },
                {
                  "name": "电机过载保护"
                },
                {
                  "name": "断电记忆与重启恢复"
                }
              ]
            }
          ]
        }
      ]
    },
    "auto_annotated": true,
    "needs_review": true
  }
]