[
  {
    "type": "image",
    "merged_json": "data/merged\\显示用量子点膜专利技术分析_罗朋_merged.json",
    "page_num": 6,
    "image_index": 0,
    "thought": "论文聚焦于量子点显示技术领域，核心围绕两大主流技术路径：量子点背光液晶显示器（QD-LCD）与量子点发光二极管显示器（QLED）。文中强调产业链一体化布局的复杂性，指出关键技术环节包括量子点材料合成、光转换膜制备、背光模组集成及器件封装等；同时突出专利情报分析（尤其PCT国家阶段）在技术预判与风险规避中的战略作用。技术演进呈现‘材料→器件→系统→产业协同’脉络，产学研合作是推动发展的关键支撑。架构应以‘量子点显示技术’为根，下分技术实现路径、核心组件、支撑体系三大支柱。",
    "tree": {
      "root": "量子点显示技术",
      "children": [
        {
          "name": "主流技术路径",
          "children": [
            {
              "name": "QD-LCD（量子点背光液晶显示器）",
              "children": [
                {
                  "name": "量子点光转换膜（QDEF/QDCC）"
                },
                {
                  "name": "蓝光LED背光集成"
                },
                {
                  "name": "光学设计与色彩管理"
                }
              ]
            },
            {
              "name": "QLED（量子点发光二极管显示器）",
              "children": [
                {
                  "name": "电致发光量子点层"
                },
                {
                  "name": "载流子传输层优化"
                },
                {
                  "name": "薄膜封装与寿命提升"
                }
              ]
            }
          ]
        },
        {
          "name": "核心组件与材料",
          "children": [
            {
              "name": "量子点合成与表面修饰"
            },
            {
              "name": "高稳定性量子点膜制备工艺"
            },
            {
              "name": "无镉/低镉环保量子点开发"
            },
            {
              "name": "基板与阻隔层材料"
            }
          ]
        },
        {
          "name": "支撑体系与产业生态",
          "children": [
            {
              "name": "专利情报分析与布局策略"
            },
            {
              "name": "PCT国际申请与国家阶段监控"
            },
            {
              "name": "产学研协同创新机制"
            },
            {
              "name": "产业链一体化整合（材料-器件-整机）"
            }
          ]
        }
      ]
    },
    "auto_annotated": true,
    "needs_review": true
  },
  {
    "type": "table",
    "merged_json": "data/merged\\显示用量子点膜专利技术分析_罗朋_merged.json",
    "page_num": 1,
    "table_index": 0,
    "thought": "表格内容为空（全为逗号分隔的空单元格），但结合上下文可知，该论文聚焦于‘量子点显示技术’领域的专利态势分析。文中反复提及的核心技术要素包括：量子点材料制备（如量子点膜、量子点发光玻璃管）、应用形式（背光模组、显示器）、关键工艺（制备方法、封装技术）以及产业化产品（量子点光学膜、QD-LCD电视）。虽无显式分类表，但可从技术链条推导出层级结构：以‘量子点显示技术’为根，下分‘材料与制备’‘器件与集成’‘应用与产品’三大类；其中‘材料与制备’含量子点合成、膜/玻璃管等载体结构；‘器件与集成’涉及背光模组、封装与驱动；‘应用与产品’指向LCD增强、QLED等终端显示设备。该分类符合专利文献中常见的‘材料→器件→系统’技术演进逻辑。",
    "tree": {
      "root": "量子点显示技术",
      "children": [
        {
          "name": "材料与制备",
          "children": [
            {
              "name": "量子点合成与表面修饰"
            },
            {
              "name": "量子点膜（QD Film）制备"
            },
            {
              "name": "量子点发光玻璃管（QD Glass Tube）"
            },
            {
              "name": "其他载体结构（如树脂、聚合物基体）"
            }
          ]
        },
        {
          "name": "器件与集成",
          "children": [
            {
              "name": "量子点背光模组（QD-LED Backlight）"
            },
            {
              "name": "封装与稳定性技术"
            },
            {
              "name": "驱动与光学设计"
            }
          ]
        },
        {
          "name": "应用与产品",
          "children": [
            {
              "name": "QD-LCD 显示器（液晶增强型）"
            },
            {
              "name": "QLED 显示器（电致发光型）"
            },
            {
              "name": "原型设备与商业化产品（如三星TV、索尼/QD Vision玻璃管）"
            }
          ]
        }
      ]
    },
    "auto_annotated": true,
    "needs_review": true
  },
  {
    "type": "table",
    "merged_json": "data/merged\\显示用量子点膜专利技术分析_罗朋_merged.json",
    "page_num": 1,
    "table_index": 1,
    "thought": "表格内容为空（全为逗号分隔的空单元格），未提供任何具体技术分类数据；但结合上下文可知，本文聚焦于‘量子点显示技术’领域，涉及的核心技术方向包括：量子点材料制备（如量子点膜、量子点发光玻璃管）、量子点在液晶显示器背光中的应用（如量子点光学膜用于提升色域与能效）、以及相关器件集成与商品化路径。文中提及的关键技术节点有：量子点膜制备与应用、量子点显示器、量子点光学膜、量子点发光玻璃管等，可归纳为以‘量子点显示技术’为根节点，下分‘材料与制备’‘器件与集成’‘应用与产品’三大类。该分类逻辑符合技术发展脉络：从基础材料→核心器件→终端应用。",
    "tree": {
      "root": "量子点显示技术",
      "children": [
        {
          "name": "材料与制备",
          "children": [
            {
              "name": "量子点合成与表面修饰"
            },
            {
              "name": "量子点膜制备技术"
            },
            {
              "name": "量子点发光玻璃管制造"
            }
          ]
        },
        {
          "name": "器件与集成",
          "children": [
            {
              "name": "量子点背光模组"
            },
            {
              "name": "量子点增强型LCD"
            },
            {
              "name": "量子点显示器（QLED）结构"
            }
          ]
        },
        {
          "name": "应用与产品",
          "children": [
            {
              "name": "量子点电视"
            },
            {
              "name": "高色域显示设备"
            },
            {
              "name": "商用显示与照明集成"
            }
          ]
        }
      ]
    },
    "auto_annotated": true,
    "needs_review": true
  },
  {
    "type": "table",
    "merged_json": "data/merged\\显示用量子点膜专利技术分析_罗朋_merged.json",
    "page_num": 2,
    "table_index": 0,
    "thought": "表格展示了15个IPC小类及其技术含义，结合上下文（量子点、显示、照明、半导体、纳米结构等关键词）及专利申请量分布（G02F最多，达1676件），可识别出核心主题为‘显示与照明技术’，尤其聚焦于新型显示（如量子点显示）、光学调控、半导体器件与纳米材料应用。技术分类逻辑呈现三层结构：顶层为功能导向的大类（如光调控、显示、照明、材料、测量），中层为具体技术方向（如光学器件、半导体、纳米结构），底层隐含应用领域（如量子点显示、车辆照明）。其中G02F（光性质调控器件）与G09G（静态显示控制）、G02B（光学元件）构成显示系统核心；F21V/F21S/F21Y共同构成照明子体系；C09K/C08K/B32B/B82Y指向材料支撑层；H01L/H05B涉及器件与光源基础；G01N/G06K为辅助检测与数据处理。因此，构建以‘新型显示与智能照明’为根节点的技术树，下分四大主干：光学调控与显示系统、照明系统、功能材料与结构、支撑技术。",
    "tree": {
      "root": "新型显示与智能照明技术",
      "children": [
        {
          "name": "光学调控与显示系统",
          "children": [
            {
              "name": "光性质调控器件（G02F）",
              "children": []
            },
            {
              "name": "光学元件与系统（G02B）",
              "children": []
            },
            {
              "name": "静态显示控制装置（G09G）",
              "children": []
            },
            {
              "name": "显示与标识装置（G09F）",
              "children": []
            }
          ]
        },
        {
          "name": "照明系统",
          "children": [
            {
              "name": "照明装置功能特征与零部件（F21V）",
              "children": []
            },
            {
              "name": "非便携式及车用照明设备（F21S）",
              "children": []
            },
            {
              "name": "光源构成与光色特性（F21Y）",
              "children": []
            },
            {
              "name": "电照明光源与电路（H05B）",
              "children": []
            }
          ]
        },
        {
          "name": "功能材料与纳米结构",
          "children": [
            {
              "name": "特种应用材料（C09K）",
              "children": []
            },
            {
              "name": "高分子配料添加剂（C08K）",
              "children": []
            },
            {
              "name": "层状复合产品（B32B）",
              "children": []
            },
            {
              "name": "纳米结构应用与制造（B82Y）",
              "children": []
            }
          ]
        },
        {
          "name": "器件基础与支撑技术",
          "children": [
            {
              "name": "半导体器件（H01L）",
              "children": []
            },
            {
              "name": "材料测试与分析（G01N）",
              "children": []
            },
            {
              "name": "图形数据读取与记录载体（G06K）",
              "children": []
            }
          ]
        }
      ]
    },
    "auto_annotated": true,
    "needs_review": true
  },
  {
    "type": "table",
    "merged_json": "data/merged\\显示用量子点膜专利技术分析_罗朋_merged.json",
    "page_num": 2,
    "table_index": 1,
    "thought": "表格本身为空白（仅含少量数字如68、8，无明确分类结构），但结合上下文‘（四）技术构成分析’及图4所列IPC分类数据（G02F、H01L、G02B等）与对应含义，可推断该领域技术分类体系基于国际专利分类（IPC）小类。核心聚焦于量子点显示/照明相关技术，主要涉及：光学调制与显示器件（G02F）、半导体器件（H01L）、光学元件系统（G02B）、照明装置（F21V）、发光材料（C09K）、纳米技术应用（B82Y）等。其中G02F（1676件）和H01L（568件）为最核心分支，反映量子点在电光调控与器件集成中的关键地位。因此，技术分类树应以‘量子点技术’为根节点，下设按功能与材料划分的IPC主导子类。",
    "tree": {
      "root": "量子点技术",
      "children": [
        {
          "name": "光学调控与显示器件",
          "children": [
            {
              "name": "电光调制与非线性光学（IPC: G02F）",
              "children": []
            },
            {
              "name": "显示控制与驱动（IPC: G09G）",
              "children": []
            },
            {
              "name": "光学元件与系统（IPC: G02B）",
              "children": []
            }
          ]
        },
        {
          "name": "半导体器件集成",
          "children": [
            {
              "name": "光电器件与半导体结构（IPC: H01L）",
              "children": []
            },
            {
              "name": "纳米尺度器件（IPC: B82Y）",
              "children": []
            }
          ]
        },
        {
          "name": "发光材料与配方",
          "children": [
            {
              "name": "发光材料（IPC: C09K）",
              "children": []
            },
            {
              "name": "高分子添加剂（IPC: C08K）",
              "children": []
            }
          ]
        },
        {
          "name": "照明系统与装置",
          "children": [
            {
              "name": "照明功能部件（IPC: F21V）",
              "children": []
            },
            {
              "name": "照明系统（IPC: F21S, F21Y）",
              "children": []
            }
          ]
        },
        {
          "name": "辅助与交叉技术",
          "children": [
            {
              "name": "识别与信息处理（IPC: G06K）",
              "children": []
            },
            {
              "name": "检测与分析（IPC: G01N）",
              "children": []
            },
            {
              "name": "电热光源（IPC: H05B）",
              "children": []
            }
          ]
        }
      ]
    },
    "auto_annotated": true,
    "needs_review": true
  }
]