{
  "title": "全球油田用聚烯烃管材专利技术现状与分析_牛承祥",
  "source_pdf": "data/raw\\全球油田用聚烯烃管材专利技术现状与分析_牛承祥.pdf",
  "pages": [
    {
      "page_num": 0,
      "text": "Oct．2024\n现代化工\n第44 卷增刊2\nModern Chemical Industry\n2024 年10 月\n全球油田用聚烯烃管材专利技术现状与分析\n牛承祥\n* ，徐典宏\n( 中国石油兰州化工研究中心，甘肃兰州730060)\n摘要: 借助智慧芽( Patsnap) 专利分析工具，从申请趋势、地区分布、技术构成、申请人、重点专利等角度分析了全球油田用\n聚烯烃管材技术领域的相关专利文献。分析结果表明，全球油田用聚烯烃管材技术依然处于高速发展阶段，中国企业拥有绝大\n部分专利权，但核心专利技术集中在美、日的专利商手中; 目前研究开发的重点是以ＲTP 管为代表的聚烯烃复合管技术，特别\n是复合管中的聚烯烃内衬管材料的选择和配料技术。聚烯烃管材核心技术由美、日等国家掌握，而中国企业虽然起步较晚，但\n申请量巨大，综合实力不容小觑。\n关键词: 油气输送; 聚烯烃; 复合管; 内衬管; 专利分析\n中图分类号: TE973; G255．53\n文献标志码: A\n文章编号: 0253－4320( 2024) S2－0024－05\nDOI: 10．16606/j．cnki．issn0253－4320．2024．S2．005\nCurrent status and analysis of patented technologies for\npolyolefin pipes used in oil fields worldwide\nNIU Cheng-xiang\n* ，XU Dian-hong\n( Lanzhou Petrochemical Ｒesearch Center，PetroChina Company Limited，Lanzhou 730060，China)\nAbstract: By means of Patsnap patent analysis tool，the relevant patent literature in the field of polyolefin pipe\ntechnology for oil fields worldwide is analyzed from the perspectives of application trends，regions distribution，\ntechnological composition，applicants，and key patents．Analysis results show that the technologies about polyolefin pipes\nfor oil fields worldwide stays still in a stage of rapid development，and Chinese enterprises have the vast majority of patent\nrights，but the companies in the United States and Jacan control the core patent technologies．At present，the research and\ndevelopment focus on polyolefin composite pipe technology represented by ＲTP pipes，especially the selection and\nbatching technology of polyolefin inner lining pipe materials in composite pipe．Although Chinese enterprises started\nrelatively late，their application volume is huge，and their comprehensive strength cannot be underestimated．\nKey words: oil and gas transportation; polyolefin; composite pipe; inner lining pipe; patent analysis\n收稿日期: 2024－04－10; 修回日期: 2024－08－26\n作者简介: 牛承祥( 1973－) ，男，本科，高级工程师，主要从事石油化工领域信息研究和专利分析工作，通讯联系人，15751947236，niuchengxiang@\npetrochina．com．cn。\n在油气工业的发展中，管道运输具备安全、环\n保、节能等优势，发挥着世界各油气生产/消费国能\n源调配的重要作用，是发展空间最大的油气运输手\n段，是继公路、铁路、航运和水运后的第5 种运输方\n式。油气输送连续管按照材质分为金属连续管和非\n金属连续管，其发展经历了高强度低合金碳钢、高强\n度低合金调质钢钛合金和复合材料3 个阶段。其\n中，采用聚烯烃树脂等非金属材料的管道系统由于\n其优异的自防腐性、良好的韧性和挠性、便利可靠的\n连接性和可施工性等特点，近年来在全球工程领域\n发展迅猛，在国内外各公司的专利布局中也占据比\n较重要的地位\n［1］。本工作从申请趋势、地区分布、\n技术功效矩阵、申请人、核心专利等多个角度，综合\n分析了国内外油田用聚烯烃管材技术的专利申请状\n况，理清了技术研发方向以及专利保护力度与布局\n范围，以期对国内聚烯烃管材技术的进一步发展提\n供理论依据。\n1\n专利分析平台\n为全面了解全球油田用聚烯烃管材技术的相关\n专利内容，本工作以Patsnap( 智慧芽) 国际专利分析\n数据库为依据，综合考虑油田用聚烯烃管材技术关\n键词以及国际专利分类号( IPC) ，制定了检索策略，\n并对数据进行了手工筛选与整理，获得了共计\n1 498 件相关专利，据此构建了全球油田用聚烯烃\n管材技术的专利数据库。\n2\n专利技术分析\n2. 1\n申请趋势\n图1 是油田用聚烯烃管材领域近20 年专利的\n申请趋势图。其中，专利授权率表明申请的有效率\n以及最终获得授权的提交申请成功率。\n·\n4\n2\n·",
      "images": []
    },
    {
      "page_num": 1,
      "text": "2024 年10 月\n牛承祥等: 全球油田用聚烯烃管材专利技术现状与分析\n图1\n油田用聚烯烃管材领域全球专利申请趋势\n注: 2023 年申请的部分专利仍处于未公开状态，其专利申请量数据仅作为参考值，下同。\n由图1 可见，排除2023 年申请的专利有一部分\n还处于未公开状态的因素，全球油田用聚烯烃管材\n领域近20 年的专利申请量总体呈明显的增长趋势。\n在2009 年之前，油田用管材主要还趋向使用金属管\n材，专用的聚烯烃管材还不是热点\n［3－4］，因此该领域\n每年的专利申请量不多，基本都在30 件以下，整体\n申请趋势处于平稳状态。2009 年以后，业内人士逐\n步认识到聚乙烯等非金属管道系统具有优异的自防\n腐性、韧性和挠性等优势，在油田领域的应用范围越\n来越大。因此油田用聚烯烃管材的研究热情逐步升\n温，专利申请数量也有逐年上升的趋势。从专利授\n权占比来看，随着近十多年专利申请数量的迅速增\n加，专利质量也良莠不齐，从2008—2017 年专利授\n权比例有逐年走低的趋势。而随着国内专利提升工\n程的普及，从2018 年开始，中国专利的申请质量提\n高显著，也带动了全球专利授权率的明显提升。\n2. 2\n地区分布\n油田用聚烯烃管材领域全球专利来源国/地区\n分布见表1。由表1 可知，油田用聚烯烃管材领域\n的专利技术最主要来源于中国、日本、德国和美国，\n而来源于中国的专利占比达到了惊人的81. 78%，\n可见中国在该领域的技术创新能力和活跃程度远远\n领先于世界其他国家和地区。该表侧面反映出该领\n域主要技术持有者应该集中分布在中国和日本。\n2. 3\n技术功效矩阵\n图2 是全球油田用聚烯烃管材领域专利技术功\n效矩阵情况( 以IPC 分类号与检索式为综合分析对\n象) 。分析该技术领域的功效矩阵情况，可以帮助\n了解各技术分支和所对应产品功效的创新热度，以\n及当前技术布局的空白点及可能的潜在机会。\n表1\n油田用聚烯烃管材领域全球专利来源国/地区分布\n专利来源国/地区\n专利数量\n占比/%\n中国\n1 046\n81. 78\n日本\n98\n7. 66\n德国\n36\n2. 81\n美国\n32\n2. 50\n俄罗斯\n23\n1. 80\n韩国\n10\n0. 78\n欧洲专利局\n8\n0. 63\n英国\n5\n0. 39\n瑞典\n5\n0. 39\n意大利\n3\n0. 23\n其他\n13\n1. 02\n图2\n全球油田用聚烯烃管材技术领域\n专利功效矩阵\n注: 图中数字为申请专利篇数。\n功效矩阵分析结果发现，全球油田用聚烯烃管\n材专利申请方向( 技术手段) 主要集中于4 种，按申\n请量从高到低依次为: 管材配料( 原料中加入的各\n·\n5\n2\n·",
      "images": [
        {
          "path": "data/processed\\全球油田用聚烯烃管材专利技术现状与分析_牛承祥_p1_i0.jpx",
          "width": 1748,
          "height": 685,
          "page": 1
        },
        {
          "path": "data/processed\\全球油田用聚烯烃管材专利技术现状与分析_牛承祥_p1_i1.jpx",
          "width": 945,
          "height": 733,
          "page": 1
        }
      ]
    },
    {
      "page_num": 2,
      "text": "现代化工\n第44 卷增刊2\n种有机、无机配料) ，刚性复合管( 包括ＲTP 管、复合\n玻璃钢管和含聚烯烃内衬的多层复合钢管) ，内衬\n管原料，复合管结构( 包括复合管的构型、构件和连\n接方式) 。而该领域的功效热点主要包括以下7 个\n方面: 强度提高，降低成本，耐热，耐磨，耐腐蚀，耐结\n垢，提高寿命。\n通过图2 功效矩阵的深度分析可知，从全球油\n田用聚烯烃管材的类型来看，刚性复合管的申请量\n占据绝对优势，其中，除了ＲTP 管的专利数量较多\n以外，将聚烯烃内衬管材制作于金属油管内壁形成\n“管中管”结构的聚烯烃内衬油管技术的专利数量\n也占较大比例。功效热点方面，刚性复合管方向的\n研究热点较为平均，在强度提高、耐结垢和提高寿命\n3 种功效的申请量稍显优势; 管材配料技术的主要\n功效热点是耐腐蚀、耐结垢和提高寿命，而在耐热和\n降低成本方面专利数量较少; 内衬管原料技术方面，\n研究热点主要集中在耐热、耐腐蚀和耐结垢等功效;\n复合管结构方面的专利数量是最少的，其中以提高\n管材强度为目的的专利申请量稍占优势，其次是耐\n结垢和提高寿命方面也占一定比例。\n在创新机会方面，图2 所示功效矩阵图中专利\n密集的区域，如通过管材配料方式提高管材的耐腐\n蚀、耐结垢性能等更适合进行改进创新。而原始创\n新适合在专利较少的区域寻找突破口，尽量避开专\n利密集区。\n2. 4\n申请人\n专利申请的数量往往可以作为公司在某一技术\n领域科研活跃程度的一个粗略指标。一般而言，企\n业在专利策略上采取的是“以数量为基础，以质量\n为核心”的策略。尽管专利数量的多寡并不能直接\n等同于技术能力的强弱，但与竞争对手在专利数量\n上存在的差距，却可能在市场竞争和侵权纠纷中为\n企业带来截然不同的处境。全球专利申请量前15\n位申请人排名见表2。\n表2\n全球专利申请量前15 位申请人排名\n排名\n申请人\n数量/件\n第1 位\n中国石化\n16\n第1 位\n赢创工业集团\n16\n第2 位\n中国石油\n12\n第2 位\n久保田株式会社\n12\n第3 位\n超科有限公司\n10\n第3 位\nPILUGIN．A．NIKOLAEVICH\n10\n第3 位\nZAMALEEV．F．USMANOVICH\n10\n第3 位\nGAYSIN M．FAVZAVIEVICH\n10\n第3 位\n广东联塑科技实业有限公司\n10\n第3 位\n可乐丽株式会社\n10\n第3 位\n武汉金牛经济发展有限公司\n10\n第4 位\n旭化成株式会社\n9\n第4 位\n日丰企业集团有限公司\n9\n第4 位\n景顺塑料制品有限公司\n9\n第5 位\n纽铂有限公司\n8\n由表2 可知，全球申请量排名前15 位的申请人\n中仅有6 位来自中国，其余9 位均来自国外。然而，\n并列排名第1 位的中国石化和赢创工业集团的申请\n量分别仅有16 件，只占全球专利总量( 1 498 件) 的\n1. 1%，且后13 位申请人的申请量差距都仅在5 件\n以内。参考贝恩行业集中度来看\n［2］，该领域的\nCＲ8 = 7. 3%，属于分散竞争型领域，技术创新并未集\n中在少数几个公司手中，市场上存在大量的创新主\n体在该领域进行试探性的发明创造，远远未达到行\n业垄断的状态。\n从国家的角度看，前15 位申请人中，除了中国\n公司总申请量为74 件排第一以外，日本公司( 久保\n田株式会社、可乐丽株式会社和旭化成株式会社)\n以31 件的申请量位居第二; 排名第三的是3 位俄罗\n斯申请人，总申请量为30 件; 而在国家/地区排名第\n三的德国只有赢创工业集团出现在申请量前15 的\n名单中; 排名第四的美国甚至没有任何申请人上榜。\n2. 5\n核心专利\n核心专利是指在产品或技术发展中具有核心作\n用的专利。核心专利是实施专利战略的基础，一个\n企业拥有的核心专利越多，它的创新能力和未来市\n场竞争力也就越强。由于核心专利一般都是产品制\n造或标准实施时的必要专利，而且基础专利也一定\n是核心专利。因此，从某领域海量专利中找出核心\n专利对于掌握该领域的核心技术及其技术拥有者具\n有非常重要的意义。但核心专利不是一个专利法意\n义上的概念，而是一个文献统计学意义上的概念。\n通常采用专利的引证分析等方法来判定、寻找核心\n专利，而被引频次则成为判断核心专利的重要指标。\n全球专利被引证次数排行见表3。\n由表3 可知，被引频次排名前10 的专利中，5\n件来自美国申请人，3 件来自日本申请人，其余2 件\n分别来自中国和德国。在全球油田用聚烯烃管材领\n域，美国专利仅以2. 5%的申请量占比排名全球的\n第4 位( 表1) ，绝对谈不上是专利申请大国，但其核\n心专利的拥有占比却令人瞩目。\n·\n6\n2\n·",
      "images": []
    },
    {
      "page_num": 3,
      "text": "2024 年10 月\n牛承祥等: 全球油田用聚烯烃管材专利技术现状与分析\n表3\n全球专利被引证次数排行\n排名\n专利号\n中文名称\n当前权利人( 申请人)\n被引次数\n1\nUS48722253A\n提高高性能油管和套管中连接段完整性的装置和方法\nCarstensen Kenneth J( 美国)\n128\n2\nUS2009038475A1\n非金属高压管道和管道衬里的现场制造和安装的方法和系统\n斯玛特管道有限公司( 美国)\n65\n2\nCN102942763A\n一种抗拉抗压耐高温改性聚丙烯管材的制备方法\n宏岳塑胶集团股份有限公司( 中国)\n65\n3\nJP2003192914A\n具有优异导电性的热塑性树脂成型\n三菱树脂株式会社( 日本)\n61\n4\nUS4882830A\n提高高性能油套管接箍段完整性的方法\nCarstensen Kenneth J( 美国)\n37\n5\nUS7600537B2\n增强塑料管\n霍尼韦尔国际公司( 美国)\n32\n5\nJP2003083199A\n燃料输送管用脉冲阻尼器\n加藤发条株式会社( 日本)\n32\n6\nUS3467764A\n用于供应燃料、油等的耐热和耐腐蚀软管接头\nTＲANSPOＲTGUMMI( 美国)\n31\n6\nUS4943489A\n具有优良的耐腐蚀性能和耐高温高压的机械性能的复合管\n久保田株式会社( 日本)\n31\n7\nDE3509774A1\n一种不锈钢、铝、塑料等材质管道的连接头\n威茨曼有限公司( 德国)\n24\n申请量排名前15 的申请人中，只有日本久保田\n株式会社的1 件专利( US4943489A) 上榜，并列排在\n被引次数的第6 位。而其他14 位申请人的专利被\n引次数都不高，均未进入上述榜单。这个现象进一\n步证明了油田用聚烯烃管材技术领域处于分散竞争\n状态，市场上竞争者众多，头部企业尚未形成。\n从专利技术角度看，表3 所列的核心专利中有\n多件都涉及高性能油田用复合管及其连接技术，其\n中包括美国Carstensen Kenneth J 的2 件专利\n( US48722253A 和US4882830A) 、美国霍尼韦尔国\n际公司的1 件专利( US7600537B2) 、美国TＲANS-\nPOＲTGUMMI 的1 件专利( US3467764A) 、日本久保\n田株式会社的1 件专利( US4943489A) 和德国威茨\n曼有限公司的1 件专利( DE3509774A1) 。\n从上述分析可知，高性能复合管及其连接技术\n已经成为全球油田用聚烯烃管材领域的核心专利技\n术。核心专利的拥有者主要以美国和日本权利人为\n主。中国申请人的专利总量虽然在全球油田用聚烯\n烃管材技术领域内遥遥领先，但只有1 件专利进入\n被引前10 榜单。说明中国申请人总体专利质量不\n高，从而在行业影响力和竞争力方面也会受到限制。\n2. 6\n行业前景\n技术生命周期分析是一种最常用的专利定量分\n析方法。通过深入剖析某行业专利技术的当前发展阶\n段，我们能够有效地预测未来的技术发展趋势和前景。\n全球油田用聚烯烃管材专利技术生命周期见图3。\n图3\n全球油田用聚烯烃管材专利技术生命周期\n由图3 可知，2003—2008 年间，油田用聚烯烃\n管材技术还处于萌芽期，那时油田用管材主要还趋\n向使用钢管、玻璃钢管。由于ＲTP 管等聚烯烃增强\n复合管材的工艺技术不成熟、产品质量不稳定、投资\n较高，市场需求低迷，市场上关于更高、更新的换代\n技术的研发情绪不高\n［1，3－4］。这时的油田用聚烯烃\n管材技术市场不明朗，研发风险大，创新主体较少，\n专利申请量和申请人数均比较少，且增速缓慢; 随着\n欧美国家在油田用聚烯烃管材技术方面的突破，中\n国油气输送行业也看到了ＲTP 等聚烯烃复合管材\n低成本、易维护的优势，看好它的发展前景。随着\n2008 年首次针对有机纤维增强的ＲTP 管起草了产\n品标准，对国内管材生产厂家研发、生产油田用聚烯\n烃管材的方向确定了目标\n［5－6］。一些厂家致力于独\n·\n7\n2\n·",
      "images": [
        {
          "path": "data/processed\\全球油田用聚烯烃管材专利技术现状与分析_牛承祥_p3_i0.jpx",
          "width": 1713,
          "height": 768,
          "page": 3
        }
      ]
    },
    {
      "page_num": 4,
      "text": "现代化工\n第44 卷增刊2\n立研发生产工艺，展现出创新的实力; 有的则选择采\n用高性能材料来打造高端产品，满足市场对高品质\n的追求; 而另一些厂家则选择成本较低的材料，走经\n济实惠的路线，以满足更广泛的市场需求。因此，市\n场上的产品种类丰富多样，性能也各有千秋。在经\n历了2009—2012 年的技术调整期后，该技术于\n2012—2020 年步入了快速发展的轨道。在这个阶\n段，技术不断取得突破，市场逐步扩大，越来越多的\n创新主体加入到该领域中来，专利申请量和申请人\n数量均呈现出井喷式的增长。2020—2022 年间\n( 2023 年申请的部分专利未公开，只作参考) ，专利\n申请量有先提高后萎缩的走向，创新主体也有所减\n少。这个时期有2 种解释，一是创新主体间竞争激\n烈，技术商品化程度非常高，部分创新主体退场，该\n技术进入了成熟期; 二是由于创新主体暂时遇到技\n术瓶颈，导致申请人数量有所回调，如同2009—\n2012 年和2015—2019 年这2 个时间段的表现一\n样，事实上该技术领域依然处于成长期。结合前文\n的各项分析判断，后者的可能性更大一些。但可以\n肯定的是，该领域的新兴技术持续出现，市场上依\n然有大量的中小型企业，且行业寡头并未形成，油\n田用聚烯烃管材技术领域远未进入到衰退期，行\n业前景看好。\n3\n结论\n( 1) 在专利拥有量方面，全球油田用聚烯烃管\n材领域主要专利持有国为中国、日本、德国和美国。\n中国专利占全球专利申请量的八成以上，说明中国\n企业的创新动力、市场意识和知识产权意识非常强\n烈。然而，该领域专利集中度较为分散，尚未形成明\n显的头部企业。\n( 2) 在研发热点方面，以ＲTP 管为主的具有聚\n烯烃内衬的刚性复合管以及管材原料的配料技术目\n前处在红海领域，专利数量最多。另外，如何提高管\n材强度和寿命，以及管材的耐热、防腐蚀、防积垢和抗\n磨损等功效是油田用聚烯烃管材的主要研究热点。\n( 3) 在核心专利的持有量方面，美国和日本申\n请人显著超过其他国家，展现出明显的领先优势。\n相比之下，尽管中国申请人的专利申请数量庞大，但\n专利质量普遍偏低，其核心专利的拥有量与整体专\n利占有率之间并未形成合理的正比关系。\n( 4) 行业前景方面，全球油田用聚烯烃管材领\n域的新兴技术持续出现，竞争也较为分散，技术市场\n上依然存在大量的中小型企业，行业寡头尚未形成，\n行业仍然处于成长期。\n参考文献\n［1］程梦鹏．油气输送ＲTP 管道技术现状及应用前景［J］．油气田地\n面工程，2016，35( 8) : 6－8．\n［2］文新雷，彭瑛．我国钢铁行业集中度与经济发展的关系探析［J］．\n现代经济信息，2011，( 9) : 198，203．\n［3］商永滨，李言，李刚，等．非金属管道在油气田中的应用［J］．内蒙\n古石油化工，2020，46( 2) : 14－18．\n［4］黄琳，孙晶，孙鹏，等．非金属复合管在油气长输管道工程中应用\n的可行性［J］．石油科技论坛，2013，32( 6) : 23－25，65．\n［5］韩方勇．油气田常用非金属管道标准体系研究［J］．石油规划设\n计，2009，20( 3) : 4－7，49．\n［6］李厚补，羊东明，戚东涛，等．增强热塑性塑料连续管标准现状及\n发展建议［J］．塑料，2016，45( 4) : 85－87，112．■\n■■■■■■■■■■■■■■■■■■■■■■■■■■■■■■■■■■■■■■■■■■■■■■■\n( 上接第23 页)\n参考文献\n［1］聂晓炜．智能油田关键技术研究现状与发展趋势［J］．油气地质\n与采收率，2022，29( 3) : 68－79．\n［2］刘宝军．智能油田建设构想［J］．胜利油田党校学报，2015，28\n( 6) : 99－101．\n［3］杨金花，邱茂鑫，赵旭，等．智能化———油气工业发展大趋势\n［J］．石油科技论坛，2016，35( 6) : 36－42．\n［4］刘慧婷，徐华，周东焱．基于“互联网+”模式下的石化行业智能\n管网的发展现状研究［J］．石化技术，2015，22( 5) : 90－91．\n［5］Axelh E H，Mauricio P．Intelligent pipeline solution: Leveraging\nbreakthrough industrial internet technologies and big data analytics\nfor safer，more efficient and gas pipeline operations［C］．Berlin:\nPipeline Technology Conference，2015: 1－12．\n［6］李剑锋．油气工业数字化智能化发展趋势［J］．石油科技论坛，\n2023，42( 3) : 10－21．\n［7］高建炜，安鹏，曲晓慧，等．海上油气业务智能化发展趋势分析\n［J］．海洋工程装备与技术，2019，6( S1) : 442－445．\n［8］王同良，杨梦露．海洋油气工程数字化智能化发展现状与展望\n［J］．前瞻科技，2023，2( 2) : 105－120．\n［9］张刘军，韩永波，田娜．长输管道完整性管理信息系统建设现状\n及发展方向［J］．石油化工与自动化，2020，56( 4) : 58－65．\n［10］宫敬，徐波，张微波．中俄东线智能化工艺运行基础与实现的思\n考［J］．油气储运，2020，39( 2) : 130－139．\n［11］宁永乔．长宁页岩气田数字化管道建设创新与实践［J］．油气田\n地面工程，2019，38( 3) : 65－68．\n［12］张涌．中国石化智能化管线管理的应用实践［J］．当代石油石\n化，2018，26( 5) : 37－40．\n［13］王珂．日仪线数字化管道可视化应用研究［D］．东营: 中国石油\n大学( 华东) ，2020．\n［14］Wang J F．Integrity management of submarine pipelines［EB /OL］．\n( 2021－09－02) ．［2023－02－13］．https: / /mp．weixin．qq．com/s?\nsrc= 11＆timestamp = 1666084822＆ver = 4112＆signature = iAYg88\nMSJnlkbB-oFWab0gQW2CaD6WG6VPzsSqNEcaVHq62y71VCizkk\n2qm7wiQa-gf9BJFhQbmkqE *\nx07eniaeh-GbXm0ANqVrＲtl-BrCh\nCLWＲaEAm5l6qhFBw3ew5＆new = 1．\n［15］吴宜营．中海油公司数智化转型路径及效果研究［D］．大连: 大\n连海事大学，2023．\n［16］贺子珊，王海龙．数字孪生技术在油田的应用现状及发展前景\n［J］．石油化工自动化，2023，59( S1) : 1－3．■\n·\n8\n2\n·",
      "images": []
    }
  ]
}